assets/banner.png
synthex/__init__.py
synthex/__version__.py
synthex/api_client.py
synthex/config.py
synthex/credits_api.py
synthex/decorators.py
synthex/endpoints.py
synthex/exceptions.py
synthex/jobs_api.py
synthex/py.typed
synthex/users_api.py
synthex/models/__init__.py
synthex/models/base.py
synthex/models/credits.py
synthex/models/jobs.py
synthex/models/responses.py
synthex/models/users.py
synthex-0.4.2.dist-info/licenses/LICENSE
tests/__init__.py
tests/conftest.py
tests/unit/__init__.py
tests/unit/base/__init__.py
tests/unit/base/test_ping_unit.py
tests/unit/base/test_synthex_config_unit.py
tests/unit/base/test_synthex_instantiation_unit.py
tests/unit/credits/__init__.py
tests/unit/credits/test_credits_unit.py
tests/unit/exceptions/__init__.py
tests/unit/exceptions/test_exceptions.py
tests/unit/jobs/__init__.py
tests/unit/jobs/test_create_job.py
tests/unit/jobs/test_generate_data_unit.py
tests/unit/jobs/test_get_data_and_write_to_file.py
tests/unit/jobs/test_get_job_data.py
tests/unit/jobs/test_list_jobs_unit.py
tests/unit/jobs/test_sanitize_output_path.py
tests/unit/jobs/test_status.py
tests/unit/users/__init__.py
tests/unit/users/test_users_unit.py
synthex-0.4.2.dist-info/METADATA
synthex-0.4.2.dist-info/WHEEL
synthex-0.4.2.dist-info/top_level.txt
synthex-0.4.2.dist-info/RECORD
