Metadata-Version: 2.4
Name: synthex
Version: 0.4.2
Summary: Generate high-quality, large-scale synthetic datasets 📊🧪
Author: Saurabh Pradhan
Author-email: Riccardo Lucato <riccardo@tanaos.com>
License: MIT
Project-URL: homepage, https://github.com/tanaos/synthex
Classifier: Development Status :: 3 - Alpha
Classifier: Intended Audience :: Developers
Classifier: License :: OSI Approved :: MIT License
Classifier: Programming Language :: Python :: 3
Classifier: Programming Language :: Python :: 3.9
Classifier: Programming Language :: Python :: 3.10
Classifier: Topic :: Software Development :: Libraries :: Python Modules
Classifier: Operating System :: OS Independent
Requires-Python: >=3.9
License-File: LICENSE
Requires-Dist: responses>=0.25.7
Requires-Dist: pydantic>=2.11.2
Requires-Dist: pydantic_settings>=2.9.1
Requires-Dist: platformdirs>=4.3.8
Requires-Dist: httpx>=0.28.1
Dynamic: license-file
